{
    "config_meta" : {
        "author" : "Justin May",
        "author_date" : "2021-08-12",
        "desc" : "Translated configuration file for FACET-II Experiment laser"
    },
    "config" : {
        "name" : "FACET S20",
        "type" : "SIM",
        "genpv_base" : "OSC:LA20:10:",
        "dev_base" : "OSC:LA20:10:",
        "matlab_pv_base" : "SIOC:SYS1:ML00:AO",
        "matlab_pv_offsets" : 451,
        "matlab_pv_digits" : 3,
        "counter_base" : "DIAG:LA20:LS22:",
        "freq_counter" : "OSC:LA20:10:FREQ_RBCK",
        "phase_motor" : "OSC:LA20:10:M1_MOTR_IQ",
        "error_pv_name" : "OSC:LA20:10:FS_STATUS",
        "version_pv_name" : "OSC:LA20:10:FS_WATCHDOG.DESC",
        "laser_trigger" : "TRIG:LA20:LS27:TDES",
        "trig_in_ticks" : false,
        "reverse_counter" : 1,
        "use_secondary_calibration" : false,
        "use_drift_correction" : false,
        "use_dither" : false,
        "timeout" : 1.0,
        "use_combined_counter" : false
    },
    "add_config" : {
        "tic_type" : "keysight"
    }
}
